cjm_graph_domains/__init__.py
cjm_graph_domains/_modidx.py
cjm_graph_domains/core.py
cjm_graph_domains/domains/__init__.py
cjm_graph_domains/domains/knowledge.py
cjm_graph_domains/domains/relations.py
cjm_graph_domains/domains/structure.py
cjm_graph_domains-0.0.3.dist-info/licenses/LICENSE
cjm_graph_domains-0.0.3.dist-info/METADATA
cjm_graph_domains-0.0.3.dist-info/WHEEL
cjm_graph_domains-0.0.3.dist-info/entry_points.txt
cjm_graph_domains-0.0.3.dist-info/top_level.txt
cjm_graph_domains-0.0.3.dist-info/RECORD
