Metadata-Version: 2.4
Name: cjm-graph-domains
Version: 0.0.3
Summary: A shared library of Pydantic models and standard schemas for the cjm-graph-plugin-system ecosystem, enabling type-safe domain definitions across plugins and UIs.
Home-page: https://github.com/cj-mills/cjm-graph-domains
Author: Christian J. Mills
Author-email: 9126128+cj-mills@users.noreply.github.com
License: Apache Software License 2.0
Keywords: nbdev jupyter notebook python
Classifier: Development Status :: 4 - Beta
Classifier: Intended Audience :: Developers
Classifier: Natural Language :: English
Classifier: Programming Language :: Python :: 3.11
Classifier: Programming Language :: Python :: 3.12
Classifier: License :: OSI Approved :: Apache Software License
Requires-Python: >=3.11
License-File: LICENSE
Requires-Dist: cjm_graph_plugin_system
Provides-Extra: dev
Dynamic: author
Dynamic: author-email
Dynamic: classifier
Dynamic: description
Dynamic: description-content-type
Dynamic: home-page
Dynamic: keywords
Dynamic: license
Dynamic: license-file
Dynamic: provides-extra
Dynamic: requires-dist
Dynamic: requires-python
Dynamic: summary
